src/register_pair.v
`timescale 1ns/1ps
module register_pair(input wire clk,rst,load,transfer,input wire [3:0] data_in,output reg [3:0] stored,value);
always @(posedge clk) if(rst) begin stored<=0;value<=0;end else begin
if(load) stored<=data_in; if(transfer) value<=stored;end
endmodule

sim/tb_register_pair.sv
`timescale 1ns/1ps
module tb_register_pair;
reg clk=0,rst=1;integer checks=0;always #5 clk=~clk;
task step;begin @(posedge clk);#1;end endtask
task check(input condition,input [8*100-1:0] description);begin
checks=checks+1;if(condition!==1'b1) begin $display("LAB2_FAIL %0s time=%0t",description,$time);$fatal(1,"check failed");end end endtask
initial begin #100000;$fatal(1,"watchdog timeout");end
reg load=0,transfer=0;reg [3:0] data_in=0;wire [3:0] stored,value;
register_pair dut(clk,rst,load,transfer,data_in,stored,value);
initial begin $dumpfile("wave.vcd");$dumpvars(0,tb_register_pair);end
initial begin
step;check({stored,value}===8'h00,"reset");rst=0;
data_in=4'ha;load=1;step;check({stored,value}===8'ha0,"load does not transfer");
load=0;data_in=4'h3;transfer=1;step;check({stored,value}===8'haa,"transfer stored not live input");
load=1;step;check({stored,value}===8'h3a,"simultaneous uses old stored");
step;check({stored,value}===8'h33,"next edge transfers new stored");
load=0;transfer=0;data_in=4'hf;step;check({stored,value}===8'h33,"both hold");
rst=1;load=1;transfer=1;step;check({stored,value}===8'h00,"reset beats both controls");
$display("LAB2_PASS register_pair checks=%0d",checks);$display("END_NS=%0d",$time);$finish;end
endmodule

evidence/vscode/normal_wave.vcd
$date
	Sun Sep 20 17:17:55 2026
$end
$version
	Icarus Verilog
$end
$timescale
	1ps
$end
$scope module tb_register_pair $end
$var wire 4 ! value [3:0] $end
$var wire 4 " stored [3:0] $end
$var reg 1 # clk $end
$var reg 4 $ data_in [3:0] $end
$var reg 1 % load $end
$var reg 1 & rst $end
$var reg 1 ' transfer $end
$var integer 32 ( checks [31:0] $end
$scope module dut $end
$var wire 1 # clk $end
$var wire 4 ) data_in [3:0] $end
$var wire 1 % load $end
$var wire 1 & rst $end
$var wire 1 ' transfer $end
$var reg 4 * stored [3:0] $end
$var reg 4 + value [3:0] $end
$upscope $end
$scope task check $end
$var reg 1 , condition $end
$var reg 800 - description [799:0] $end
$upscope $end
$scope task step $end
$upscope $end
$upscope $end
$enddefinitions $end
$comment Show the parameter values. $end
$dumpall
$end
#0
$dumpvars
bx -
x,
bx +
bx *
b0 )
b0 (
0'
1&
0%
b0 $
0#
bx "
bx !
$end
#5000
b0 !
b0 +
b0 "
b0 *
1#
#6000
1%
b1010 $
b1010 )
0&
b1 (
b111001001100101011100110110010101110100 -
1,
#10000
0#
#15000
b1010 "
b1010 *
1#
#16000
1'
b11 $
b11 )
0%
b10 (
b1101100011011110110000101100100001000000110010001101111011001010111001100100000011011100110111101110100001000000111010001110010011000010110111001110011011001100110010101110010 -
#20000
0#
#25000
b1010 !
b1010 +
1#
#26000
1%
b11 (
b11101000111001001100001011011100111001101100110011001010111001000100000011100110111010001101111011100100110010101100100001000000110111001101111011101000010000001101100011010010111011001100101001000000110100101101110011100000111010101110100 -
#30000
0#
#35000
b11 "
b11 *
1#
#36000
b100 (
b1110011011010010110110101110101011011000111010001100001011011100110010101101111011101010111001100100000011101010111001101100101011100110010000001101111011011000110010000100000011100110111010001101111011100100110010101100100 -
#40000
0#
#45000
b11 !
b11 +
1#
#46000
b1111 $
b1111 )
0'
0%
b101 (
b11011100110010101111000011101000010000001100101011001000110011101100101001000000111010001110010011000010110111001110011011001100110010101110010011100110010000001101110011001010111011100100000011100110111010001101111011100100110010101100100 -
#50000
0#
#55000
1#
#56000
1'
1%
1&
b110 (
b11000100110111101110100011010000010000001101000011011110110110001100100 -
#60000
0#
#65000
b0 !
b0 +
b0 "
b0 *
1#
#66000
b111 (
b1110010011001010111001101100101011101000010000001100010011001010110000101110100011100110010000001100010011011110111010001101000001000000110001101101111011011100111010001110010011011110110110001110011 -
